txtflar/__init__.py
txtflar/__main__.py
txtflar/cli.py
txtflar/txtflar.py
txtflar-1.1.1.dist-info/LICENSE.txt
txtflar-1.1.1.dist-info/METADATA
txtflar-1.1.1.dist-info/WHEEL
txtflar-1.1.1.dist-info/entry_points.txt
txtflar-1.1.1.dist-info/top_level.txt
txtflar-1.1.1.dist-info/RECORD
