Metadata-Version: 2.1
Name: txtflar
Version: 1.1.1
Summary: TeXT file language-aware rename
Home-page: https://github.com/ldotlopez/txtflar
Author: Luis López
Author-email: luis@cuarentaydos.com
Project-URL: Bug Tracker, https://github.com/ldotlopez/txtflar/issues
Classifier: Programming Language :: Python :: 3
Classifier: License :: OSI Approved :: GNU General Public License v2 or later (GPLv2+)
Classifier: Operating System :: OS Independent
Requires-Python: >=3.5
License-File: LICENSE.txt
Requires-Dist: babelfish (>=0.5.5)
Requires-Dist: chardet (>=2.3.0)
Requires-Dist: langdetect (>=1.0.6)
